mpld3/__about__.py
mpld3/__init__.py
mpld3/_display.py
mpld3/_server.py
mpld3/mpld3renderer.py
mpld3/plugins.py
mpld3/urls.py
mpld3/utils.py
mpld3/js/d3.v3.min.js
mpld3/js/d3.v5.min.js
mpld3/js/mpld3.v0.5.9.js
mpld3/js/mpld3.v0.5.9.min.js
mpld3/mplexporter/__init__.py
mpld3/mplexporter/_py3k_compat.py
mpld3/mplexporter/convertors.py
mpld3/mplexporter/exporter.py
mpld3/mplexporter/tools.py
mpld3/mplexporter/utils.py
mpld3/mplexporter/renderers/__init__.py
mpld3/mplexporter/renderers/base.py
mpld3/mplexporter/renderers/fake_renderer.py
mpld3/mplexporter/renderers/vega_renderer.py
mpld3/mplexporter/renderers/vincent_renderer.py
mpld3-0.5.9.dist-info/AUTHORS.md
mpld3-0.5.9.dist-info/LICENSE
mpld3-0.5.9.dist-info/METADATA
mpld3-0.5.9.dist-info/WHEEL
mpld3-0.5.9.dist-info/top_level.txt
mpld3-0.5.9.dist-info/RECORD
